README.rst
setup.cfg
setup.py
pysift/__init__.py
pysift/api.py
pysift/core.py
pysift/errors.py
pysift.egg-info/PKG-INFO
pysift.egg-info/SOURCES.txt
pysift.egg-info/dependency_links.txt
pysift.egg-info/not-zip-safe
pysift.egg-info/requires.txt
pysift.egg-info/top_level.txt