Metadata-Version: 1.1
Name: pysift
Version: 0.0.2
Summary: SiftScience API.
Home-page: http://github.com/rhyselsmore/pysift
Author: Rhys Elsmore
Author-email: me@rhys.io
License: MIT
Platform: UNKNOWN
Classifier: Development Status :: 5 - Production/Stable
Classifier: Intended Audience :: Developers
Classifier: Natural Language :: English
Classifier: License :: OSI Approved :: Apache Software License
Classifier: Programming Language :: Python
Classifier: Programming Language :: Python :: 2.6
Classifier: Programming Language :: Python :: 2.7
Classifier: Programming Language :: Python :: 3
Classifier: Programming Language :: Python :: 3.3
